csexamgenerator/__init__.py
csexamgenerator/main.py
csexamgenerator-2.1.0.dist-info/LICENSE
csexamgenerator-2.1.0.dist-info/METADATA
csexamgenerator-2.1.0.dist-info/WHEEL
csexamgenerator-2.1.0.dist-info/top_level.txt
csexamgenerator-2.1.0.dist-info/RECORD
