Metadata-Version: 2.1
Name: csexamgenerator
Version: 2.1.0
Summary: An internal tool for exam submission
Author: Obiwan
Author-email: quan.do@coderschool.vn
License-File: LICENSE
